numbin/__init__.py
numbin/codec.py
numbin/msg_ext.py
numbin/py.typed
numbin-0.5.0.dist-info/LICENSE
numbin-0.5.0.dist-info/METADATA
numbin-0.5.0.dist-info/WHEEL
numbin-0.5.0.dist-info/top_level.txt
numbin-0.5.0.dist-info/RECORD
