Metadata-Version: 2.1
Name: numbin
Version: 0.5.0
Summary: an efficient binary serialization format for numerical data
Author-email: Keming <kemingy94@gmail.com>
License: Apache-2.0
Project-URL: homepage, https://mosecorg.github.io/numbin
Project-URL: documentation, https://mosecorg.github.io/numbin
Project-URL: repository, https://github.com/mosecorg/numbin
Project-URL: changelog, https://github.com/mosecorg/numbin/releases
Keywords: machine learning,deep learning,serialization
Classifier: Intended Audience :: Developers
Classifier: Intended Audience :: Science/Research
Classifier: License :: OSI Approved :: Apache Software License
Classifier: Programming Language :: Python :: 3 :: Only
Classifier: Programming Language :: Python :: 3.7
Classifier: Programming Language :: Python :: 3.8
Classifier: Programming Language :: Python :: 3.9
Classifier: Programming Language :: Python :: 3.10
Classifier: Programming Language :: Python :: 3.11
Classifier: Programming Language :: Python :: Implementation :: CPython
Classifier: Topic :: Scientific/Engineering :: Artificial Intelligence
Classifier: Topic :: Software Development :: Libraries :: Python Modules
Requires-Python: >=3.7
License-File: LICENSE
Requires-Dist: numpy >=1.21.1
Provides-Extra: bench
Requires-Dist: msgpack >=1.0.4 ; extra == 'bench'
Requires-Dist: numpy ; extra == 'bench'
Requires-Dist: safetensors ; extra == 'bench'
Requires-Dist: msgpack-numpy ; extra == 'bench'
Provides-Extra: dev
Requires-Dist: ruff >=0.2.2 ; extra == 'dev'
Requires-Dist: pytest >=7.1 ; extra == 'dev'
Provides-Extra: msgpack
Requires-Dist: msgpack >=1.0.4 ; extra == 'msgpack'
